verilogFolder/verilogProj/FirFilter.v
module fir_filter (
    input wire clk,
    input wire rst_n,
    input wire signed [11:0] data_in,
    output reg signed [11:0] data_out
);

    // 1. Define Coefficients as individual constants
    // 29 coefficients from Python FIR computations
    localparam signed [15:0] C0  = -61,  C1  = -68,  C2  = -79,  C3  = -78,  C4  = -35;
    localparam signed [15:0] C5  = 79,   C6  = 293,  C7  = 621,  C8  = 1059, C9  = 1580;
    localparam signed [15:0] C10 = 2138, C11 = 2670, C12 = 3111, C13 = 3402, C14 = 3504;
    localparam signed [15:0] C15 = 3402, C16 = 3111, C17 = 2670, C18 = 2138, C19 = 1580;
    localparam signed [15:0] C20 = 1059, C21 = 621,  C22 = 293,  C23 = 79,   C24 = -35;
    localparam signed [15:0] C25 = -78,  C26 = -79,  C27 = -68,  C28 = -61;

    // 2. Internal Memory
    reg signed [11:0] delay_line [0:28];
    reg signed [12:0] centered_data;
    reg signed [32:0] accumulator;
    integer i;

    always @(posedge clk or negedge rst_n) begin
        if (!rst_n) begin
            data_out <= 0;
            centered_data <= 0;
            accumulator <= 0;
            for (i=0; i<29; i=i+1) delay_line[i] <= 0;
        end else begin
            // --- STEP A: BIAS CORRECTION ---
            // Input is 0 to 4095. Subtract 2048 to center it at 0.
            centered_data <= $signed({1'b0, data_in}) - 13'sd2048;

            // --- STEP B: SHIFT REGISTER ---
            delay_line[0] <= centered_data[11:0];
            for (i=1; i<29; i=i+1) delay_line[i] <= delay_line[i-1];

            // --- STEP C: MULTIPLY AND ACCUMULATE (MAC) ---
            // We do the math manually to ensure Icarus understands it
            accumulator = (delay_line[0] * C0)   + (delay_line[1] * C1)   + (delay_line[2] * C2)   + 
                          (delay_line[3] * C3)   + (delay_line[4] * C4)   + (delay_line[5] * C5)   + 
                          (delay_line[6] * C6)   + (delay_line[7] * C7)   + (delay_line[8] * C8)   + 
                          (delay_line[9] * C9)   + (delay_line[10] * C10) + (delay_line[11] * C11) + 
                          (delay_line[12] * C12) + (delay_line[13] * C13) + (delay_line[14] * C14) + 
                          (delay_line[15] * C15) + (delay_line[16] * C16) + (delay_line[17] * C17) + 
                          (delay_line[18] * C18) + (delay_line[19] * C19) + (delay_line[20] * C20) + 
                          (delay_line[21] * C21) + (delay_line[22] * C22) + (delay_line[23] * C23) + 
                          (delay_line[24] * C24) + (delay_line[25] * C25) + (delay_line[26] * C26) + 
                          (delay_line[27] * C27) + (delay_line[28] * C28);

            // --- STEP D: OUTPUT SCALING ---
            // Shift down by 15 bits (coefficient scale) and add 2048 bias back
            data_out <= (accumulator[26:15]) + 12'sd2048;
        end
    end
endmodule

verilogFolder/verilogProj/movingAverageTb.v
`timescale 1ns/1ps

module tb_moving_avg;

    reg clk;
    reg rst_n;
    reg signed [11:0] tb_data_in;
    wire signed [11:0] tb_data_out;

    // 1. Create a "Memory Array" to hold the file data
    // Depth is 2400 (matches your 0.05s @ 48kHz signal)
    reg [11:0] test_memory [0:2399];
    integer i;

    fir_filter uut (
        .clk(clk),
        .rst_n(rst_n),
        .data_in(tb_data_in),
        .data_out(tb_data_out)
    );

    always #10 clk = ~clk; // 50MHz Clock

    initial begin
        // Initialize
        clk = 0;
        rst_n = 0;
        tb_data_in = 0;

        // 2. LOAD THE FILE into test_memory
        $readmemh("input_signal.hex", test_memory);
        $display("Loaded %d samples from hex file", 2400);

        #100 rst_n = 1; // Release reset

        // 3. FEED DATA: Loop through the memory
        for (i = 0; i < 2400; i = i + 1) begin
            @(posedge clk);
            tb_data_in = test_memory[i];
        end

        $display("Processing Complete.");
        $finish;
    end

    initial begin
        $dumpfile("moving_avg_sim.vcd");
        $dumpvars(0, tb_moving_avg);
    end

endmodule

verilogFolder/verilogProj/moving_avg_sim.vcd
$date
	Mon Mar 09 11:29:39 2026
$end
$version
	Icarus Verilog
$end
$timescale
	1ps
$end
$scope module tb_moving_avg $end
$var wire 12 ! tb_data_out [11:0] $end
$var reg 1 " clk $end
$var reg 1 # rst_n $end
$var reg 12 $ tb_data_in [11:0] $end
$var integer 32 % i [31:0] $end
$scope module uut $end
$var wire 1 " clk $end
$var wire 12 & data_in [11:0] $end
$var wire 1 # rst_n $end
$var parameter 16 ' C0 $end
$var parameter 16 ( C1 $end
$var parameter 16 ) C10 $end
$var parameter 16 * C11 $end
$var parameter 16 + C12 $end
$var parameter 16 , C13 $end
$var parameter 16 - C14 $end
$var parameter 16 . C15 $end
$var parameter 16 / C16 $end
$var parameter 16 0 C17 $end
$var parameter 16 1 C18 $end
$var parameter 16 2 C19 $end
$var parameter 16 3 C2 $end
$var parameter 16 4 C20 $end
$var parameter 16 5 C21 $end
$var parameter 16 6 C22 $end
$var parameter 16 7 C23 $end
$var parameter 16 8 C24 $end
$var parameter 16 9 C25 $end
$var parameter 16 : C26 $end
$var parameter 16 ; C27 $end
$var parameter 16 < C28 $end
$var parameter 16 = C3 $end
$var parameter 16 > C4 $end
$var parameter 16 ? C5 $end
$var parameter 16 @ C6 $end
$var parameter 16 A C7 $end
$var parameter 16 B C8 $end
$var parameter 16 C C9 $end
$var reg 33 D accumulator [32:0] $end
$var reg 13 E centered_data [12:0] $end
$var reg 12 F data_out [11:0] $end
$var integer 32 G i [31:0] $end
$upscope $end
$upscope $end
$enddefinitions $end
$comment Show the parameter values. $end
$dumpall
b11000101100 C
b10000100011 B
b1001101101 A
b100100101 @
b1001111 ?
b1111111111011101 >
b1111111110110010 =
b1111111111000011 <
b1111111110111100 ;
b1111111110110001 :
b1111111110110010 9
b1111111111011101 8
b1001111 7
b100100101 6
b1001101101 5
b10000100011 4
b1111111110110001 3
b11000101100 2
b100001011010 1
b101001101110 0
b110000100111 /
b110101001010 .
b110110110000 -
b110101001010 ,
b110000100111 +
b101001101110 *
b100001011010 )
b1111111110111100 (
b1111111111000011 '
$end
#0
$dumpvars
b11101 G
b0 F
b0 E
b0 D
b0 &
bx %
b0 $
0#
0"
b0 !
$end
#10000
b11101 G
1"
#20000
0"
#30000
b11101 G
1"
#40000
0"
#50000
b11101 G
1"
#60000
0"
#70000
b11101 G
1"
#80000
0"
#90000
b11101 G
1"
#100000
0"
b0 %
1#
#110000
b100000000000 !
b100000000000 F
b1001010110 E
b11101 G
b1 %
b101001010110 $
b101001010110 &
1"
#120000
0"
#130000
b111010000 E
b11101 G
b10 %
b100111010000 $
b100111010000 &
1"
#140000
0"
#150000
b11111111110 !
b11111111110 F
b1111011001110 E
b111111111111111110111000110000010 D
b11101 G
b11 %
b11011001110 $
b11011001110 &
1"
#160000
0"
#170000
b11111111101 !
b11111111101 F
b1111100 E
b111111111111111101111001010011000 D
b11101 G
b100 %
b100001111100 $
b100001111100 &
1"
#180000
0"
#190000
b11111111110 !
b11111111110 F
b10011000110 E
b111111111111111110001010100100000 D
b11101 G
b101 %
b110011000110 $
b110011000110 &
1"
#200000
0"
#210000
b11111111101 !
b11111111101 F
b1100000010 E
b111111111111111101110111001011000 D
b11101 G
b110 %
b101100000010 $
b101100000010 &
1"
#220000
0"
#230000
b11111111100 !
b11111111100 F
b10001110100 E
b111111111111111100011101100101110 D
b11101 G
b111 %
b110001110100 $
b110001110100 &
1"
#240000
0"
#250000
b11111111101 !
b11111111101 F
b110010100 E
b111111111111111101011010000000000 D
b11101 G
b1000 %
b100110010100 $
b100110010100 &
1"
#260000
0"
#270000
b11111111111 !
b11111111111 F
b1100110111 E
b111111111111111111110101001100110 D
b11101 G
b1001 %
b101100110111 $
b101100110111 &
1"
#280000
0"
#290000
b100000000110 !
b100000000110 F
b1111110011 E
b110101110101000110 D
b11101 G
b1010 %
b101111110011 $
b101111110011 &
1"
#300000
0"
#310000
b100000010001 !
b100000010001 F
b10011111010 E
b10001011011001110111 D
b11101 G
b1011 %
b110011111010 $
b110011111010 &
1"
#320000
0"
#330000
b100000100001 !
b100000100001 F
b10111101101 E
b100001111111000100111 D
b11101 G
b1100 %
b110111101101 $
b110111101101 &
1"
#340000
0"
#350000
b100000111010 !
b100000111010 F
b10001100111 E
b111010000000000100011 D
b11101 G
b1101 %
b110001100111 $
b110001100111 &
1"
#360000
0"
#370000
b100001011010 !
b100001011010 F
b1000100000 E
b1011010101111111111000 D
b11101 G
b1110 %
b101000100000 $
b101000100000 &
1"
#380000
0"
#390000
b100010000110 !
b100010000110 F
b11000101000 E
b10000110001111101011110 D
b11101 G
b1111 %
b111000101000 $
b111000101000 &
1"
#400000
0"
#410000
b100010111101 !
b100010111101 F
b11001110011 E
b10111101001011100110011 D
b11101 G
b10000 %
b111001110011 $
b111001110011 &
1"
#420000
0"
#430000
b100011111100 !
b100011111100 F
b10010100101 E
b11111100100100101111001 D
b11101 G
b10001 %
b110010100101 $
b110010100101 &
1"
#440000
0"
#450000
b100101000101 !
b100101000101 F
b10001101011 E
b101000101010010101000000 D
b11101 G
b10010 %
b110001101011 $
b110001101011 &
1"
#460000
0"
#470000
b100110010110 !
b100110010110 F
b10110110100 E
b110010110100101100100111 D
b11101 G
b10011 %
b110110110100 $
b110110110100 &
1"
#480000
0"
#490000
b100111101101 !
b100111101101 F
b111111100 E
b111101101011000110100011 D
b11101 G
b10100 %
b100111111100 $
b100111111100 &
1"
#500000
0"
#510000
b101001000110 !
b101001000110 F
b110001111 E
b1001000110101000000000101 D
b11101 G
b10101 %
b100110001111 $
b100110001111 &
1"
#520000
0"
#530000
b101010100010 !
b101010100010 F
b10000111011 E
b1010100010000100101100010 D
b11101 G
b10110 %
b110000111011 $
b110000111011 &
1"
#540000
0"
#550000
b101011111011 !
b101011111011 F
b1001000111 E
b1011111011111101000101001 D
b11101 G
b10111 %
b101001000111 $
b101001000111 &
1"
#560000
0"
#570000
b101101010000 !
b101101010000 F
b1010010 E
b1101010000110001110111111 D
b11101 G
b11000 %
b100001010010 $
b100001010010 &
1"
#580000
0"
#590000
b101110100000 !
b101110100000 F
b1110110011011 E
b1110100000101100001000101 D
b11101 G
b11001 %
b10110011011 $
b10110011011 &
1"
#600000
0"
#610000
b101111101001 !
b101111101001 F
b1110101011010 E
b1111101001011011001110111 D
b11101 G
b11010 %
b10101011010 $
b10101011010 &
1"
#620000
0"
#630000
b110000101001 !
b110000101001 F
b1111101001010 E
b10000101001010011011001111 D
b11101 G
b11011 %
b11101001010 $
b11101001010 &
1"
#640000
0"
#650000
b110001011100 !
b110001011100 F
b1101111010111 E
b10001011100111111100010100 D
b11101 G
b11100 %
b1111010111 $
b1111010111 &
1"
#660000
0"
#670000
b110010000001 !
b110010000001 F
b1110100011000 E
b10010000001000110011111100 D
b11101 G
b11101 %
b10100011000 $
b10100011000 &
1"
#680000
0"
#690000
b110010010101 !
b110010010101 F
b1111101000000 E
b10010010101010000110101010 D
b11101 G
b11110 %
b11101000000 $
b11101000000 &
1"
#700000
0"
#710000
b110010010100 !
b110010010100 F
b1101111110110 E
b10010010100001011110011001 D
b11101 G
b11111 %
b1111110110 $
b1111110110 &
1"
#720000
0"
#730000
b110001111011 !
b110001111011 F
b1111010100111 E
b10001111011100001101100101 D
b11101 G
b100000 %
b11010100111 $
b11010100111 &
1"
#740000
0"
#750000
b110001001001 !
b110001001001 F
b1110001110111 E
b10001001001111110001010110 D
b11101 G
b100001 %
b10001110111 $
b10001110111 &
1"
#760000
0"
#770000
b101111111001 !
b101111111001 F
b1101100011001 E
b1111111001100101111001011 D
b11101 G
b100010 %
b1100011001 $
b1100011001 &
1"
#780000
0"
#790000
b101110001110 !
b101110001110 F
b1110011001010 E
b1110001110101100111110111 D
b11101 G
b100011 %
b10011001010 $
b10011001010 &
1"
#800000
0"
#810000
b101100001100 !
b101100001100 F
b1101111000100 E
b1100001100001101101000100 D
b11101 G
b100100 %
b1111000100 $
b1111000100 &
1"
#820000
0"
#830000
b101001110010 !
b101001110010 F
b1100100011010 E
b1001110010011110000111100 D
b11101 G
b100101 %
b100011010 $
b100011010 &
1"
#840000
0"
#850000
b100111001010 !
b100111001010 F
b1101000010010 E
b111001010101100111101101 D
b11101 G
b100110 %
b1000010010 $
b1000010010 &
1"
#860000
0"
#870000
b100100011011 !
b100100011011 F
b1110010100010 E
b100011011000000011001010 D
b11101 G
b100111 %
b10010100010 $
b10010100010 &
1"
#880000
0"
#890000
b100001101011 !
b100001101011 F
b1101111010111 E
b1101011100000000111101 D
b11101 G
b101000 %
b1111010111 $
b1111010111 &
1"
#900000
0"
#910000
b11111000010 !
b11111000010 F
b1110000100101 E
b111111111111000010010000000000100 D
b11101 G
b101001 %
b10000100101 $
b10000100101 &
1"
#920000
0"
#930000
b11100100110 !
b11100100110 F
b1101100010000 E
b111111111100100110011001100000011 D
b11101 G
b101010 %
b1100010000 $
b1100010000 &
1"
#940000
0"
#950000
b11010011010 !
b11010011010 F
b1110111111110 E
b111111111010011010101001011011110 D
b11101 G
b101011 %
b10111111110 $
b10111111110 &
1"
#960000
0"
#970000
b11000011111 !
b11000011111 F
b1110011001000 E
b111111111000011111010111101011010 D
b11101 G
b101100 %
b10011001000 $
b10011001000 &
1"
#980000
0"
#990000
b10110110001 !
b10110110001 F
b1111011000011 E
b111111110110110001000100010100011 D
b11101 G
b101101 %
b11011000011 $
b11011000011 &
1"
#1000000
0"
#1010000
b10101010010 !
b10101010010 F
b1110100111000 E
b111111110101010010001010100111110 D
b11101 G
b101110 %
b10100111000 $
b10100111000 &
1"
#1020000
0"
#1030000
b10011111100 !
b10011111100 F
b1111101111100 E
b111111110011111100111101000000111 D
b11101 G
b101111 %
b11101111100 $
b11101111100 &
1"
#1040000
0"
#1050000
b10010110000 !
b10010110000 F
b1110000000100 E
b111111110010110000000100010000011 D
b11101 G
b110000 %
b10000000100 $
b10000000100 &
1"
#1060000
0"
#1070000
b10001101001 !
b10001101001 F
b1111011001000 E
b111111110001101001110000000100000 D
b11101 G
b110001 %
b11011001000 $
b11011001000 &
1"
#1080000
0"
#1090000
b10000101110 !
b10000101110 F
b101101110 E
b111111110000101110010000110000110 D
b11101 G
b110010 %
b100101101110 $
b100101101110 &
1"
#1100000
0"
#1110000
b1111111010 !
b1111111010 F
b1111101100101 E
b111111101111111010101111111001001 D
b11101 G
b110011 %
b11101100101 $
b11101100101 &
1"
#1120000
0"
#1130000
b1111010011 !
b1111010011 F
b10100011111 E
b111111101111010011111110001101100 D
b11101 G
b110100 %
b110100011111 $
b110100011111 &
1"
#1140000
0"
#1150000
b1111000000 !
b1111000000 F
b1111100 E
b111111101111000000111001001101001 D
b11101 G
b110101 %
b100001111100 $
b100001111100 &
1"
#1160000
0"
#1170000
b1110111110 !
b1110111110 F
b1001011010 E
b111111101110111110001101001110001 D
b11101 G
b110110 %
b101001011010 $
b101001011010 &
1"
#1180000
0"
#1190000
b1111010001 !
b1111010001 F
b1000001000 E
b111111101111010001111000001111000 D
b11101 G
b110111 %
b101000001000 $
b101000001000 &
1"
#1200000
0"
#1210000
b1111110111 !
b1111110111 F
b111101111 E
b111111101111110111110010011100101 D
b11101 G
b111000 %
b100111101111 $
b100111101111 &
1"
#1220000
0"
#1230000
b10000110000 !
b10000110000 F
b1101001010 E
b111111110000110000010101100101000 D
b11101 G
b111001 %
b101101001010 $
b101101001010 &
1"
#1240000
0"
#1250000
b10001111010 !
b10001111010 F
b10011110101 E
b111111110001111010010000001110000 D
b11101 G
b111010 %
b110011110101 $
b110011110101 &
1"
#1260000
0"
#1270000
b10011001111 !
b10011001111 F
b1111010000 E
b111111110011001111101101110110010 D
b11101 G
b111011 %
b101111010000 $
b101111010000 &
1"
#1280000
0"
#1290000
b10100110000 !
b10100110000 F
b1101001100 E
b111111110100110000100010101001100 D
b11101 G
b111100 %
b101101001100 $
b101101001100 &
1"
#1300000
0"
#1310000
b10110011100 !
b10110011100 F
b11001001011 E
b111111110110011100100100111011011 D
b11101 G
b111101 %
b111001001011 $
b111001001011 &
1"
#1320000
0"
#1330000
b11000001111 !
b11000001111 F
b10100100110 E
b111111111000001111011101010111110 D
b11101 G
b111110 %
b110100100110 $
b110100100110 &
1"
#1340000
0"
#1350000
b11010001001 !
b11010001001 F
b10111111100 E
b111111111010001001001010111111110 D
b11101 G
b111111 %
b110111111100 $
b110111111100 &
1"
#1360000
0"
#1370000
b11100001000 !
b11100001000 F
b1111100001 E
b111111111100001000000100101100001 D
b11101 G
b1000000 %
b101111100001 $
b101111100001 &
1"
#1380000
0"
#1390000
b11110001001 !
b11110001001 F
b1011000000 E
b111111111110001001110111011000100 D
b11101 G
b1000001 %
b101011000000 $
b101011000000 &
1"
#1400000
0"
#1410000
b100000001111 !
b100000001111 F
b10010101010 E
b1111011011101010000 D
b11101 G
b1000010 %
b110010101010 $
b110010101010 &
1"
#1420000
0"
#1430000
b100010010101 !
b100010010101 F
b10101001001 E
b10010101001011011010010 D
b11101 G
b1000011 %
b110101001001 $
b110101001001 &
1"
#1440000
0"
#1450000
b100100010110 !
b100100010110 F
b10000000101 E
b100010110110111011000101 D
b11101 G
b1000100 %
b110000000101 $
b110000000101 &
1"
#1460000
0"
#1470000
b100110010100 !
b100110010100 F
b10001010 E
b110010100110111001110001 D
b11101 G
b1000101 %
b100010001010 $
b100010001010 &
1"
#1480000
0"
#1490000
b101000001110 !
b101000001110 F
b1111101 E
b1000001110111001101110011 D
b11101 G
b1000110 %
b100001111101 $
b100001111101 &
1"
#1500000
0"
#1510000
b101010000010 !
b101010000010 F
b1000010011 E
b1010000010111010110101011 D
b11101 G
b1000111 %
b101000010011 $
b101000010011 &
1"
#1520000
0"
#1530000
b101011101110 !
b101011101110 F
b110010100 E
b1011101110100001001010110 D
b11101 G
b1001000 %
b100110010100 $
b100110010100 &
1"
#1540000
0"
#1550000
b101101001110 !
b101101001110 F
b1111010111011 E
b1101001110111110001101101 D
b11101 G
b1001001 %
b11010111011 $
b11010111011 &
1"
#1560000
0"
#1570000
b101110100101 !
b101110100101 F
b1110001111001 E
b1110100101011000100000101 D
b11101 G
b1001010 %
b10001111001 $
b10001111001 &
1"
#1580000
0"
#1590000
b101111101110 !
b101111101110 F
b100111111 E
b1111101110101001010100000 D
b11101 G
b1001011 %
b100100111111 $
b100100111111 &
1"
#1600000
0"
#1610000
b110000101001 !
b110000101001 F
b1110110001000 E
b10000101001010011010010101 D
b11101 G
b1001100 %
b10110001000 $
b10110001000 &
1"
#1620000
0"
#1630000
b110001001101 !
b110001001101 F
b1111001100110 E
b10001001101101001110110000 D
b11101 G
b1001101 %
b11001100110 $
b11001100110 &
1"
#1640000
0"
#1650000
b110001011110 !
b110001011110 F
b1101001100100 E
b10001011110100011010001011 D
b11101 G
b1001110 %
b1001100100 $
b1001100100 &
1"
#1660000
0"
#1670000
b110001010100 !
b110001010100 F
b1111101110000 E
b10001010100010110011111011 D
b11101 G
b1001111 %
b11101110000 $
b11101110000 &
1"
#1680000
0"
#1690000
b110000110010 !
b110000110010 F
b1110001110110 E
b10000110010101000000111011 D
b11101 G
b1010000 %
b10001110110 $
b10001110110 &
1"
#1700000
0"
#1710000
b101111110101 !
b101111110101 F
b1101010000111 E
b1111110101000010111101100 D
b11101 G
b1010001 %
b1010000111 $
b1010000111 &
1"
#1720000
0"
#1730000
b101110011110 !
b101110011110 F
b1110001001101 E
b1110011110101000111101110 D
b11101 G
b1010010 %
b10001001101 $
b10001001101 &
1"
#1740000
0"
#1750000
b101100110101 !
b101100110101 F
b1110101000100 E
b1100110101100101011000110 D
b11101 G
b1010011 %
b10101000100 $
b10101000100 &
1"
#1760000
0"
#1770000
b101010110111 !
b101010110111 F
b1100100100110 E
b1010110111010000110100011 D
b11101 G
b1010100 %
b100100110 $
b100100110 &
1"
#1780000
0"
#1790000
b101000101011 !
b101000101011 F
b1100011111000 E
b1000101011101101011111001 D
b11101 G
b1010101 %
b11111000 $
b11111000 &
1"
#1800000
0"
#1810000
b100110011000 !
b100110011000 F
b1101011001010 E
b110011000101101100011000 D
b11101 G
b1010110 %
b1011001010 $
b1011001010 &
1"
#1820000
0"
#1830000
b100100000001 !
b100100000001 F
b1111000110111 E
b100000001000011111110110 D
b11101 G
b1010111 %
b11000110111 $
b11000110111 &
1"
#1840000
0"
#1850000
b100001101000 !
b100001101000 F
b1110011100101 E
b1101000101011100001000 D
b11101 G
b1011000 %
b10011100101 $
b10011100101 &
1"
#1860000
0"
#1870000
b11111010010 !
b11111010010 F
b1101010110110 E
b111111111111010010100001010101010 D
b11101 G
b1011001 %
b1010110110 $
b1010110110 &
1"
#1880000
0"
#1890000
b11101000001 !
b11101000001 F
b1110010011111 E
b111111111101000001011111010000110 D
b11101 G
b1011010 %
b10010011111 $
b10010011111 &
1"
#1900000
0"
#1910000
b11010110111 !
b11010110111 F
b1111011100000 E
b111111111010110111100001010101001 D
b11101 G
b1011011 %
b11011100000 $
b11011100000 &
1"
#1920000
0"
#1930000
b11000110101 !
b11000110101 F
b1101111001100 E
b111111111000110101000101001111100 D
b11101 G
b1011100 %
b1111001100 $
b1111001100 &
1"
#1940000
0"
#1950000
b10110111001 !
b10110111001 F
b1111000001101 E
b111111110110111001000001010100010 D
b11101 G
b1011101 %
b11000001101 $
b11000001101 &
1"
#1960000
0"
#1970000
b10101000111 !
b10101000111 F
b1110111101110 E
b111111110101000111100110111010001 D
b11101 G
b1011110 %
b10111101110 $
b10111101110 &
1"
#1980000
0"
#1990000
b10011011110 !
b10011011110 F
b1110110110010 E
b111111110011011110010101111100110 D
b11101 G
b1011111 %
b10110110010 $
b10110110010 &
1"
#2000000
0"
#2010000
b10010000000 !
b10010000000 F
b1110000111000 E
b111111110010000000100110000110001 D
b11101 G
b1100000 %
b10000111000 $
b10000111000 &
1"
#2020000
0"
#2030000
b10000110010 !
b10000110010 F
b1111100010100 E
b111111110000110010011010011011001 D
b11101 G
b1100001 %
b11100010100 $
b11100010100 &
1"
#2040000
0"
#2050000
b1111110110 !
b1111110110 F
b1111100001110 E
b111111101111110110100011001100001 D
b11101 G
b1100010 %
b11100001110 $
b11100001110 &
1"
#2060000
0"
#2070000
b1111001100 !
b1111001100 F
b1000010 E
b111111101111001100111001011010101 D
b11101 G
b1100011 %
b100001000010 $
b100001000010 &
1"
#2080000
0"
#2090000
b1110110111 !
b1110110111 F
b1000011100 E
b111111101110110111000110000111000 D
b11101 G
b1100100 %
b101000011100 $
b101000011100 &
1"
#2100000
0"
#2110000
b1110110110 !
b1110110110 F
b101100011 E
b111111101110110110001000110000101 D
b11101 G
b1100101 %
b100101100011 $
b100101100011 &
1"
#2120000
0"
#2130000
b1111001000 !
b1111001000 F
b1100101100 E
b111111101111001000110100001100101 D
b11101 G
b1100110 %
b101100101100 $
b101100101100 &
1"
#2140000
0"
#2150000
b1111101100 !
b1111101100 F
b10001001011 E
b111111101111101100110011101110101 D
b11101 G
b1100111 %
b110001001011 $
b110001001011 &
1"
#2160000
0"
#2170000
b10000011100 !
b10000011100 F
b1111001101 E
b111111110000011100000100000111110 D
b11101 G
b1101000 %
b101111001101 $
b101111001101 &
1"
#2180000
0"
#2190000
b10001010011 !
b10001010011 F
b11010001110 E
b111111110001010011100101011000110 D
b11101 G
b1101001 %
b111010001110 $
b111010001110 &
1"
#2200000
0"
#2210000
b10010010100 !
b10010010100 F
b1111010100 E
b111111110010010100011010001001110 D
b11101 G
b1101010 %
b101111010100 $
b101111010100 &
1"
#2220000
0"
#2230000
b10011010111 !
b10011010111 F
b1101010001 E
b111111110011010111110110011100101 D
b11101 G
b1101011 %
b101101010001 $
b101101010001 &
1"
#2240000
0"
#2250000
b10100100010 !
b10100100010 F
b10111101010 E
b111111110100100010110101001001100 D
b11101 G
b1101100 %
b110111101010 $
b110111101010 &
1"
#2260000
0"
#2270000
b10101110011 !
b10101110011 F
b11000110111 E
b111111110101110011111100101110001 D
b11101 G
b1101101 %
b111000110111 $
b111000110111 &
1"
#2280000
0"
#2290000
b10111010001 !
b10111010001 F
b10100111011 E
b111111110111010001000101100001000 D
b11101 G
b1101110 %
b110100111011 $
b110100111011 &
1"
#2300000
0"
#2310000
b11000111011 !
b11000111011 F
b1000010010 E
b111111111000111011000010111010111 D
b11101 G
b1101111 %
b101000010010 $
b101000010010 &
1"
#2320000
0"
#2330000
b11010110101 !
b11010110101 F
b1011000010 E
b111111111010110101000010111111101 D
b11101 G
b1110000 %
b101011000010 $
b101011000010 &
1"
#2340000
0"
#2350000
b11101000010 !
b11101000010 F
b1001010110 E
b111111111101000010100001000001001 D
b11101 G
b1110001 %
b101001010110 $
b101001010110 &
1"
#2360000
0"
#2370000
b11111011111 !
b11111011111 F
b10011101000 E
b111111111111011111111100111001111 D
b11101 G
b1110010 %
b110011101000 $
b110011101000 &
1"
#2380000
0"
#2390000
b100010000111 !
b100010000111 F
b100101111 E
b10000111110101011101100 D
b11101 G
b1110011 %
b100100101111 $
b100100101111 &
1"
#2400000
0"
#2410000
b100100110100 !
b100100110100 F
b1110000111 E
b100110100011011100101010 D
b11101 G
b1110100 %
b101110000111 $
b101110000111 &
1"
#2420000
0"
#2430000
b100111100001 !
b100111100001 F
b1111000000 E
b111100001110110010111101 D
b11101 G
b1110101 %
b101111000000 $
b101111000000 &
1"
#2440000
0"
#2450000
b101010000101 !
b101010000101 F
b1100001010 E
b1010000101110111001111101 D
b11101 G
b1110110 %
b101100001010 $
b101100001010 &
1"
#2460000
0"
#2470000
b101100010111 !
b101100010111 F
b1111011000101 E
b1100010111100010001010011 D
b11101 G
b1110111 %
b11011000101 $
b11011000101 &
1"
#2480000
0"
#2490000
b101110010000 !
b101110010000 F
b1111110010101 E
b1110010000000101011000001 D
b11101 G
b1111000 %
b11110010101 $
b11110010101 &
1"
#2500000
0"
#2510000
b101111101110 !
b101111101110 F
b1001110 E
b1111101110010001011100011 D
b11101 G
b1111001 %
b100001001110 $
b100001001110 &
1"
#2520000
0"
#2530000
b110000101110 !
b110000101110 F
b1111010111001 E
b10000101110000010001001100 D
b11101 G
b1111010 %
b11010111001 $
b11010111001 &
1"
#2540000
0"
#2550000
b110001001101 !
b110001001101 F
b1111101111000 E
b10001001101101000110101100 D
b11101 G
b1111011 %
b11101111000 $
b11101111000 &
1"
#2560000
0"
#2570000
b110001010011 !
b110001010011 F
b1111100001100 E
b10001010011010101111001010 D
b11101 G
b1111100 %
b11100001100 $
b11100001100 &
1"
#2580000
0"
#2590000
b110001000000 !
b110001000000 F
b1110000000001 E
b10001000000111000000011010 D
b11101 G
b1111101 %
b10000000001 $
b10000000001 &
1"
#2600000
0"
#2610000
b110000011011 !
b110000011011 F
b1101111100100 E
b10000011011000001110100101 D
b11101 G
b1111110 %
b1111100100 $
b1111100100 &
1"
#2620000
0"
#2630000
b101111100110 !
b101111100110 F
b1101001101010 E
b1111100110001011010001001 D
b11101 G
b1111111 %
b1001101010 $
b1001101010 &
1"
#2640000
0"
#2650000
b101110100110 !
b101110100110 F
b1111000101010 E
b1110100110000110001111010 D
b11101 G
b10000000 %
b11000101010 $
b11000101010 &
1"
#2660000
0"
#2670000
b101101011100 !
b101101011100 F
b1101111100000 E
b1101011100010000110011001 D
b11101 G
b10000001 %
b1111100000 $
b1111100000 &
1"
#2680000
0"
#2690000
b101100000111 !
b101100000111 F
b1110100010000 E
b1100000111111111001000101 D
b11101 G
b10000010 %
b10100010000 $
b10100010000 &
1"
#2700000
0"
#2710000
b101010101100 !
b101010101100 F
b1111001000101 E
b1010101100010010001011100 D
b11101 G
b10000011 %
b11001000101 $
b11001000101 &
1"
#2720000
0"
#2730000
b101001000101 !
b101001000101 F
b1111010100111 E
b1001000101100010110000110 D
b11101 G
b10000100 %
b11010100111 $
b11010100111 &
1"
#2740000
0"
#2750000
b100111010011 !
b100111010011 F
b1101011001001 E
b111010011111100101110000 D
b11101 G
b10000101 %
b1011001001 $
b1011001001 &
1"
#2760000
0"
#2770000
b100101010111 !
b100101010111 F
b1110001111010 E
b101010111010011100000011 D
b11101 G
b10000110 %
b10001111010 $
b10001111010 &
1"
#2780000
0"
#2790000
b100011010001 !
b100011010001 F
b1110001111011 E
b11010001100101101010110 D
b11101 G
b10000111 %
b10001111011 $
b10001111011 &
1"
#2800000
0"
#2810000
b100001000100 !
b100001000100 F
b1110100001111 E
b1000100100010111001001 D
b11101 G
b10001000 %
b10100001111 $
b10100001111 &
1"
#2820000
0"
#2830000
b11110110010 !
b11110110010 F
b1101111110101 E
b111111111110110010101100101101101 D
b11101 G
b10001001 %
b1111110101 $
b1111110101 &
1"
#2840000
0"
#2850000
b11100100010 !
b11100100010 F
b1101110100011 E
b111111111100100010010110110100001 D
b11101 G
b10001010 %
b1110100011 $
b1110100011 &
1"
#2860000
0"
#2870000
b11010011011 !
b11010011011 F
b1110110010101 E
b111111111010011011100111011010011 D
b11101 G
b10001011 %
b10110010101 $
b10110010101 &
1"
#2880000
0"
#2890000
b11000100010 !
b11000100010 F
b1110010000010 E
b111111111000100010111110000111111 D
b11101 G
b10001100 %
b10010000010 $
b10010000010 &
1"
#2900000
0"
#2910000
b10110111011 !
b10110111011 F
b1110110001001 E
b111111110110111011000101000100011 D
b11101 G
b10001101 %
b10110001001 $
b10110001001 &
1"
#2920000
0"
#2930000
b10101100110 !
b10101100110 F
b1111101000110 E
b111111110101100110101101110011010 D
b11101 G
b10001110 %
b11101000110 $
b11101000110 &
1"
#2940000
0"
#2950000
b10100100110 !
b10100100110 F
b1111000001101 E
b111111110100100110011101001011010 D
b11101 G
b10001111 %
b11000001101 $
b11000001101 &
1"
#2960000
0"
#2970000
b10011110111 !
b10011110111 F
b1110111100000 E
b111111110011110111100001000011100 D
b11101 G
b10010000 %
b10111100000 $
b10111100000 &
1"
#2980000
0"
#2990000
b10011011001 !
b10011011001 F
b1001001 E
b111111110011011001010100001001110 D
b11101 G
b10010001 %
b100001001001 $
b100001001001 &
1"
#3000000
0"
