verilogFolder/verilogProj/movingAverage.v
module moving_avg (
    input wire clk,                // System Clock
    input wire rst_n,              // Active-low Reset
    input wire signed [11:0] data_in,   // 12-bit ADC Input
    output reg signed [11:0] data_out   // 12-bit Filtered Output
);

    // 1. Internal Storage (The "Pipe")
    reg signed [11:0] shift_reg [0:3]; // 0 to 3 is the 4 tap filter, created previously
    
    // 2. Intermediate Sum (14-bit to prevent overflow)
    reg signed [13:0] sum;

    // 3. The Synchronous Logic Block
    always @(posedge clk or negedge rst_n) begin
        if (!rst_n) begin
            // Reset state: Clear everything
            data_out <= 12'd0;
            sum <= 14'd0;
            shift_reg[0] <= 12'd0;
            shift_reg[1] <= 12'd0;
            shift_reg[2] <= 12'd0;
            shift_reg[3] <= 12'd0;
        end else begin
            // A. Shifting Logic: Move old data down the line
            shift_reg[0] <= data_in;      // Newest sample enters
            shift_reg[1] <= shift_reg[0]; // Sample 0 moves to 1
            shift_reg[2] <= shift_reg[1]; // Sample 1 moves to 2
            shift_reg[3] <= shift_reg[2]; // Sample 2 moves to 3

            // B. Summation Logic
            sum <= shift_reg[0] + shift_reg[1] + shift_reg[2] + shift_reg[3];

            // C. Division Logic (Right shift by 2 = Divide by 4)
            data_out <= sum[13:2]; 
        end
    end

endmodule

verilogFolder/verilogProj/movingAverageTb.v
`timescale 1ns/1ps  // Define time units

module tb_moving_avg;

    // 1. Signals for the "Virtual FPGA"
    reg clk;
    reg rst_n;
    reg signed [11:0] tb_data_in;
    wire signed [11:0] tb_data_out;

    // 2. Instantiate your Filter (Connect the "Box")
    moving_avg uut (
        .clk(clk),
        .rst_n(rst_n),
        .data_in(tb_data_in),
        .data_out(tb_data_out)
    );

    // 3. Clock Generation (100MHz = 10ns period) 
    // since it flips every 5ns, a full cycle (up and down) takes 10ns, our 100MHz heartbeat
    always #5 clk = ~clk;

    // 4. THE MAIN PROCESS
    initial begin
        // Initialize signals
        clk = 0;
        rst_n = 0;
        tb_data_in = 0;

        // Release Reset after 20ns
        #20 rst_n = 1;

        // Load your Python data!
        // We will simulate 500 samples
        repeat (500) begin
            @(posedge clk);
            // In a real test, we'd read from the file here
            // For now, let's just send a test value
            tb_data_in = $random % 2048; 
        end

        $display("Simulation Finished");
        $finish;
    end

    // 5. Generate a waveform file for GTKWave
    initial begin
        $dumpfile("simulation_result.vcd");
        $dumpvars(0, tb_moving_avg);
    end

endmodule

verilogFolder/verilogProj/simulation_result.vcd
$date
	Fri Mar 06 16:51:45 2026
$end
$version
	Icarus Verilog
$end
$timescale
	1ps
$end
$scope module tb_moving_avg $end
$var wire 12 ! tb_data_out [11:0] $end
$var reg 1 " clk $end
$var reg 1 # rst_n $end
$var reg 12 $ tb_data_in [11:0] $end
$scope module uut $end
$var wire 1 " clk $end
$var wire 12 % data_in [11:0] $end
$var wire 1 # rst_n $end
$var reg 12 & data_out [11:0] $end
$var reg 14 ' sum [13:0] $end
$upscope $end
$upscope $end
$enddefinitions $end
$comment Show the parameter values. $end
$dumpall
$end
#0
$dumpvars
b0 '
b0 &
b0 %
b0 $
0#
0"
b0 !
$end
#5000
1"
#10000
0"
#15000
1"
#20000
0"
1#
#25000
b10100100100 $
b10100100100 %
1"
#30000
0"
#35000
b10100100100 '
b111010000001 $
b111010000001 %
1"
#40000
0"
#45000
b101001001 !
b101001001 &
b1110100101 '
b111000001001 $
b111000001001 %
1"
#50000
0"
#55000
b11101001 !
b11101001 &
b110101110 '
b111001100011 $
b111001100011 %
1"
#60000
0"
#65000
b1101011 !
b1101011 &
b10001 '
b1100001101 $
b1100001101 %
1"
#70000
0"
#75000
b100 !
b100 &
b11110111111010 '
b110001101 $
b110001101 %
1"
#80000
0"
#85000
b111101111110 !
b111101111110 &
b100000110 '
b110001100101 $
b110001100101 %
1"
#90000
0"
#95000
b1000001 !
b1000001 &
b11111101100010 '
b101000010010 $
b101000010010 %
1"
#100000
0"
#105000
b111111011000 !
b111111011000 &
b11101100010001 '
b1100000001 $
b1100000001 %
1"
#110000
0"
#115000
b111011000100 !
b111011000100 &
b11101100000101 '
b10100001101 $
b10100001101 %
1"
#120000
0"
#125000
b111011000001 !
b111011000001 &
b11111010000101 '
b101110110 $
b101110110 %
1"
#130000
0"
#135000
b111110100001 !
b111110100001 &
b1110010110 '
b10100111101 $
b10100111101 %
1"
#140000
0"
#145000
b11100101 !
b11100101 &
b111011000001 '
b11111101101 $
b11111101101 %
1"
#150000
0"
#155000
b1110110000 !
b1110110000 &
b1001110101101 '
b11110001100 $
b11110001100 %
1"
#160000
0"
#165000
b10011101011 !
b10011101011 &
b1011000101100 '
b111111001 $
b111111001 %
1"
#170000
0"
#175000
b10110001011 !
b10110001011 &
b1011010101111 '
b110011000110 $
b110011000110 %
1"
#180000
0"
#185000
b10110101011 !
b10110101011 &
b111000111000 '
b110011000101 $
b110011000101 %
1"
#190000
0"
#195000
b1110001110 !
b1110001110 &
b1100010000 '
b101010101010 $
b101010101010 %
1"
#200000
0"
#205000
b11000100 !
b11000100 &
b11011000101110 '
b11111100101 $
b11111100101 %
1"
#210000
0"
#215000
b110110001011 !
b110110001011 &
b11110000011010 '
b101001110111 $
b101001110111 %
1"
#220000
0"
#225000
b111100000110 !
b111100000110 &
b11100111001011 '
b111000010010 $
b111000010010 %
1"
#230000
0"
#235000
b111001110010 !
b111001110010 &
b11101100011000 '
b1110001111 $
b1110001111 %
1"
#240000
0"
#245000
b111011000110 !
b111011000110 &
b1111111101 '
b111110010 $
b111110010 %
1"
#250000
0"
#255000
b11111111 !
b11111111 &
b11111000001010 '
b111011001110 $
b111011001110 %
1"
#260000
0"
#265000
b111110000010 !
b111110000010 &
b1001100001 '
b101011101000 $
b101011101000 %
1"
#270000
0"
#275000
b10011000 !
b10011000 &
b11111100110111 '
b111011000101 $
b111011000101 %
1"
#280000
0"
#285000
b111111001101 !
b111111001101 &
b11101001101101 '
b101011100 $
b101011100 %
1"
#290000
0"
#295000
b111010011011 !
b111010011011 &
b11100111010111 '
b100010111101 $
b100010111101 %
1"
#300000
0"
#305000
b111001110101 !
b111001110101 &
b11001111000110 '
b100000101101 $
b100000101101 %
1"
#310000
0"
#315000
b110011110001 !
b110011110001 &
b11000100001011 '
b111001100101 $
b111001100101 %
1"
#320000
0"
#325000
b110001000010 !
b110001000010 &
b11000010101011 '
b101001100011 $
b101001100011 %
1"
#330000
0"
#335000
b110000101010 !
b110000101010 &
b10100110110010 '
b11100001010 $
b11100001010 %
1"
#340000
0"
#345000
b101001101100 !
b101001101100 &
b11011111111111 '
b101010000000 $
b101010000000 %
1"
#350000
0"
#355000
b110111111111 !
b110111111111 &
b11101001010010 '
b100100000 $
b100100000 %
1"
#360000
0"
#365000
b111010010100 !
b111010010100 &
b11110100001101 '
b10110101010 $
b10110101010 %
1"
#370000
0"
#375000
b111101000011 !
b111101000011 &
b100001010100 '
b110010011101 $
b110010011101 %
1"
#380000
0"
#385000
b1000010101 !
b1000010101 &
b11110111100111 '
b111010010110 $
b111010010110 %
1"
#390000
0"
#395000
b111101111001 !
b111101111001 &
b111111101 '
b100000010011 $
b100000010011 %
1"
#400000
0"
#405000
b1111111 !
b1111111 &
b11100011110000 '
b100000001101 $
b100000001101 %
1"
#410000
0"
#415000
b111000111100 !
b111000111100 &
b10101101010011 '
b111001010011 $
b111001010011 %
1"
#420000
0"
#425000
b101011010100 !
b101011010100 &
b10110100001001 '
b10101101011 $
b10101101011 %
1"
#430000
0"
#435000
b101101000010 !
b101101000010 &
b11001111011110 '
b101011010101 $
b101011010101 %
1"
#440000
0"
#445000
b110011110111 !
b110011110111 &
b11011010100000 '
b101000000010 $
b101000000010 %
1"
#450000
0"
#455000
b110110101000 !
b110110101000 &
b11100010010101 '
b111010101110 $
b111010101110 %
1"
#460000
0"
#465000
b111000100101 !
b111000100101 &
b11100011110000 '
b100011101 $
b100011101 %
1"
#470000
0"
#475000
b111000111100 !
b111000111100 &
b11010010100010 '
b101011001111 $
b101011001111 %
1"
#480000
0"
#485000
b110100101000 !
b110100101000 &
b11010010011100 '
b100100011 $
b100100011 %
1"
#490000
0"
#495000
b110100100111 !
b110100100111 &
b11101110111101 '
b10100001010 $
b10100001010 %
1"
#500000
0"
#505000
b111011101111 !
b111011101111 &
b1000011001 '
b101011001010 $
b101011001010 %
1"
#510000
0"
#515000
b10000110 !
b10000110 &
b11101111000110 '
b110000111100 $
b110000111100 %
1"
#520000
0"
#525000
b111011110001 !
b111011110001 &
b11110100110011 '
b10111110010 $
b10111110010 %
1"
#530000
0"
#535000
b111101001100 !
b111101001100 &
b1000000010 '
b110001010 $
b110001010 %
1"
#540000
0"
#545000
b10000000 !
b10000000 &
b11111010000010 '
b1101000001 $
b1101000001 %
1"
#550000
0"
#555000
b111110100000 !
b111110100000 &
b11011111001 '
b110011011000 $
b110011011000 %
1"
#560000
0"
#565000
b110111110 !
b110111110 &
b11110010101 '
b1101111000 $
b1101111000 %
1"
#570000
0"
#575000
b111100101 !
b111100101 &
b10100011011 '
b101010001001 $
b101010001001 %
1"
#580000
0"
#585000
b101000110 !
b101000110 &
b11111000011010 '
b10111101011 $
b10111101011 %
1"
#590000
0"
#595000
b111110000110 !
b111110000110 &
b11000100 '
b10110110110 $
b10110110110 %
1"
#600000
0"
#605000
b110001 !
b110001 &
b100110100010 '
b111000110 $
b111000110 %
1"
#610000
0"
#615000
b1001101000 !
b1001101000 &
b11111110000 '
b1110101110 $
b1110101110 %
1"
#620000
0"
#625000
b111111100 !
b111111100 &
b1000100010101 '
b101010111100 $
b101010111100 %
1"
#630000
0"
#635000
b10001000101 !
b10001000101 &
b10111100110 '
b10100101010 $
b10100101010 %
1"
#640000
0"
#645000
b101111001 !
b101111001 &
b10101011010 '
b101000001011 $
b101000001011 %
1"
#650000
0"
#655000
b101010110 !
b101010110 &
b11110110011111 '
b111001110001 $
b111001110001 %
1"
#660000
0"
#665000
b111101100111 !
b111101100111 &
b11100001100010 '
b110000101 $
b110000101 %
1"
#670000
0"
#675000
b111000011000 !
b111000011000 &
b11111100101011 '
b10101001111 $
b10101001111 %
1"
#680000
0"
#685000
b111111001010 !
b111111001010 &
b11111101010000 '
b100000111011 $
b100000111011 %
1"
#690000
0"
#695000
b111111010100 !
b111111010100 &
b11110110000000 '
b1100111010 $
b1100111010 %
1"
#700000
0"
#705000
b111101100000 !
b111101100000 &
b1001001001 '
b101001111110 $
b101001111110 %
1"
#710000
0"
#715000
b10010010 !
b10010010 &
b11101101000010 '
b1100010101 $
b1100010101 %
1"
#720000
0"
#725000
b111011010000 !
b111011010000 &
b11100100001000 '
b1111110001 $
b1111110001 %
1"
#730000
0"
#735000
b111001000010 !
b111001000010 &
b10010111110 '
b1111011001 $
b1111011001 %
1"
#740000
0"
#745000
b100101111 !
b100101111 &
b10101011101 '
b11101100010 $
b11101100010 %
1"
#750000
0"
#755000
b101010111 !
b101010111 &
b1001001000001 '
b1101001100 $
b1101001100 %
1"
#760000
0"
#765000
b10010010000 !
b10010010000 &
b1001001111000 '
b10110011111 $
b10110011111 %
1"
#770000
0"
#775000
b10010011110 !
b10010011110 &
b1010000100110 '
b110001111 $
b110001111 %
1"
#780000
0"
#785000
b10100001001 !
b10100001001 &
b1000111011100 '
b111111000 $
b111111000 %
1"
#790000
0"
#795000
b10001110111 !
b10001110111 &
b110001110010 '
b100010110111 $
b100010110111 %
1"
#800000
0"
#805000
b1100011100 !
b1100011100 &
b111011101 '
b111010011111 $
b111010011111 %
1"
#810000
0"
#815000
b1110111 !
b1110111 &
b11101011011101 '
b110001011100 $
b110001011100 %
1"
#820000
0"
#825000
b111010110111 !
b111010110111 &
b11010110101010 '
b100001011011 $
b100001011011 %
1"
#830000
0"
#835000
b110101101010 !
b110101101010 &
b10110000001101 '
b11110001001 $
b11110001001 %
1"
#840000
0"
#845000
b101100000011 !
b101100000011 &
b11101011011111 '
b101001001001 $
b101001001001 %
1"
#850000
0"
#855000
b111010110111 !
b111010110111 &
b11011010001001 '
b111011010000 $
b111011010000 %
1"
#860000
0"
#865000
b110110100010 !
b110110100010 &
b11100011111101 '
b100011010111 $
b100011010111 %
1"
#870000
0"
#875000
b111000111111 !
b111000111111 &
b11100101111001 '
b110001010001 $
b110001010001 %
1"
#880000
0"
#885000
b111001011110 !
b111001011110 &
b10111001000001 '
b11110010110 $
b11110010110 %
1"
#890000
0"
#895000
b101110010000 !
b101110010000 &
b11101110001110 '
b11100001100 $
b11100001100 %
1"
#900000
0"
#905000
b111011100011 !
b111011100011 &
b1111001010 '
b111011000010 $
b111011000010 %
1"
#910000
0"
#915000
b11110010 !
b11110010 &
b100110110101 '
b10111001000 $
b10111001000 %
1"
#920000
0"
#925000
b1001101101 !
b1001101101 &
b1001100101100 '
b101001110111 $
b101001110111 %
1"
#930000
0"
#935000
b10011001011 !
b10011001011 &
b11000001101 '
b10100111101 $
b10100111101 %
1"
#940000
0"
#945000
b110000011 !
b110000011 &
b10000111110 '
b1100010010 $
b1100010010 %
1"
#950000
0"
#955000
b100001111 !
b100001111 &
b100010001110 '
b100001111110 $
b100001111110 %
1"
#960000
0"
#965000
b1000100011 !
b1000100011 &
b11101101000100 '
b101101101 $
b101101101 %
1"
#970000
0"
#975000
b111011010001 !
b111011010001 &
b1000111010 '
b11100111001 $
b11100111001 %
1"
#980000
0"
#985000
b10001110 !
b10001110 &
b10000110110 '
b11100011111 $
b11100011111 %
1"
#990000
0"
#995000
b100001101 !
b100001101 &
b100001000011 '
b111011010011 $
b111011010011 %
1"
#1000000
0"
#1005000
b1000010000 !
b1000010000 &
b111010011000 '
b11110000101 $
b11110000101 %
1"
#1010000
0"
#1015000
b1110100110 !
b1110100110 &
b1010010110000 '
b100001111000 $
b100001111000 %
1"
#1020000
0"
#1025000
b10100101100 !
b10100101100 &
b10111101111 '
b101011011 $
b101011011 %
1"
#1030000
0"
#1035000
b101111011 !
b101111011 &
b101011 '
b1101001001 $
b1101001001 %
1"
#1040000
0"
#1045000
b1010 !
b1010 &
b10010100001 '
b111000111111 $
b111000111111 %
1"
#1050000
0"
#1055000
b100101000 !
b100101000 &
b11101101011011 '
b11100101010 $
b11100101010 %
1"
#1060000
0"
#1065000
b111011010110 !
b111011010110 &
b101000001101 '
b1101011000 $
b1101011000 %
1"
#1070000
0"
#1075000
b1010000011 !
b1010000011 &
b110000001010 '
b100010000110 $
b100010000110 %
1"
#1080000
0"
#1085000
b1100000010 !
b1100000010 &
b101000111 '
b110010001110 $
b110010001110 %
1"
#1090000
0"
#1095000
b1010001 !
b1010001 &
b11111110010110 '
b101010011100 $
b101010011100 %
1"
#1100000
0"
#1105000
b111111100101 !
b111111100101 &
b11001100001000 '
b111111010 $
b111111010 %
1"
#1110000
0"
#1115000
b110011000010 !
b110011000010 &
b11000110101010 '
b110000100110 $
b110000100110 %
1"
#1120000
0"
#1125000
b110001101010 !
b110001101010 &
b11010101001010 '
b11101110011 $
b11101110011 %
1"
#1130000
0"
#1135000
b110101010010 !
b110101010010 &
b101111 '
b110010100011 $
b110010100011 %
1"
#1140000
0"
#1145000
b1011 !
b1011 &
b1000110110 '
b100000101111 $
b100000101111 %
1"
#1150000
0"
#1155000
b10001101 !
b10001101 &
b11100001101011 '
b101010110011 $
b101010110011 %
1"
#1160000
0"
#1165000
b111000011010 !
b111000011010 &
b11011011111000 '
b111001011111 $
b111001011111 %
1"
#1170000
0"
#1175000
b110110111110 !
b110110111110 &
b10110111100100 '
b10101000100 $
b10101000100 %
1"
#1180000
0"
#1185000
b101101111001 !
b101101111001 &
b11011010000101 '
b10111110111 $
b10111110111 %
1"
#1190000
0"
#1195000
b110110100001 !
b110110100001 &
b10001001101 '
b111011001011 $
b111011001011 %
1"
#1200000
0"
#1205000
b100010011 !
b100010011 &
b100001100101 '
b101011100110 $
b101011100110 %
1"
#1210000
0"
#1215000
b1000011001 !
b1000011001 &
b10011101100 '
b1101011010 $
b1101011010 %
1"
#1220000
0"
#1225000
b100111011 !
b100111011 &
b1100000010 '
b100101001 $
b100101001 %
1"
#1230000
0"
#1235000
b11000000 !
b11000000 &
b11111000110100 '
b101011101101 $
b101011101101 %
1"
#1240000
0"
#1245000
b111110001101 !
b111110001101 &
b11101001010110 '
b110011011010 $
b110011011010 %
1"
#1250000
0"
#1255000
b111010010101 !
b111010010101 &
b11110001001010 '
b111001100101 $
b111001100101 %
1"
#1260000
0"
#1265000
b111100010010 !
b111100010010 &
b11011101010101 '
b101010110101 $
b101010110101 %
1"
#1270000
0"
#1275000
b110111010101 !
b110111010101 &
b11000011100001 '
b110011011111 $
b110011011111 %
1"
#1280000
0"
#1285000
b110000111000 !
b110000111000 &
b11001011010011 '
b101111001 $
b101111001 %
1"
#1290000
0"
#1295000
b110010110100 !
b110010110100 &
b11011101110010 '
b11101000100 $
b11101000100 %
1"
#1300000
0"
#1305000
b110111011100 !
b110111011100 &
b1010001 '
b110011010000 $
b110011010000 %
1"
#1310000
0"
#1315000
b10100 !
b10100 &
b1001101100 '
b1100101010 $
b1100101010 %
1"
#1320000
0"
#1325000
b10011011 !
b10011011 &
b100010110111 '
b10110101011 $
b10110101011 %
1"
#1330000
0"
#1335000
b1000101101 !
b1000101101 &
b110011101001 '
b11100001110 $
b11100001110 %
1"
#1340000
0"
#1345000
b1100111010 !
b1100111010 &
b110010110011 '
b10111011100 $
b10111011100 %
1"
#1350000
0"
#1355000
b1100101100 !
b1100101100 &
b1010110111111 '
b110010011010 $
b110010011010 %
1"
#1360000
0"
#1365000
b10101101111 !
b10101101111 &
b111100101111 '
b101011111101 $
b101011111101 %
1"
#1370000
0"
#1375000
b1111001011 !
b1111001011 &
b10010000001 '
b101011000011 $
b101011000011 %
1"
#1380000
0"
#1385000
b100100000 !
b100100000 &
b11100000110110 '
b10101010110 $
b10101010110 %
1"
#1390000
0"
#1395000
b111000001101 !
b111000001101 &
b11011110110000 '
b101001110 $
b101001110 %
1"
#1400000
0"
#1405000
b110111101100 !
b110111101100 &
b11110001100100 '
b111001100111 $
b111001100111 %
1"
#1410000
0"
#1415000
b111100011001 !
b111100011001 &
b11111111001110 '
b110000001010 $
b110000001010 %
1"
#1420000
0"
#1425000
b111111110011 !
b111111110011 &
b100010101 '
b110110110 $
b110110110 %
1"
#1430000
0"
#1435000
b1000101 !
b1000101 &
b11110101110101 '
b101000111000 $
b101000111000 %
1"
#1440000
0"
#1445000
b111101011101 !
b111101011101 &
b11011001011111 '
b11101111001 $
b11101111001 %
1"
#1450000
0"
#1455000
b110110010111 !
b110110010111 &
b11111101110001 '
b110010111000 $
b110010111000 %
1"
#1460000
0"
#1465000
b111111011100 !
b111111011100 &
b11111 '
b11110010100 $
b11110010100 %
1"
#1470000
0"
#1475000
b111 !
b111 &
b10111111101 '
b10110010011 $
b10110010011 %
1"
#1480000
0"
#1485000
b101111111 !
b101111111 &
b1000101011000 '
b110000000100 $
b110000000100 %
1"
#1490000
0"
#1495000
b10001010110 !
b10001010110 &
b10111100011 '
b101001011001 $
b101001011001 %
1"
#1500000
0"
#1505000
b101111000 !
b101111000 &
b1110000100 '
b111011011 $
b111011011 %
1"
#1510000
0"
#1515000
b11100001 !
b11100001 &
b11110111001011 '
b111001001101 $
b111001001101 %
1"
#1520000
0"
#1525000
b111101110010 !
b111101110010 &
b11011010000101 '
b11111011001 $
b11111011001 %
1"
#1530000
0"
#1535000
b110110100001 !
b110110100001 &
b1001011010 '
b111001101101 $
b111001101101 %
1"
#1540000
0"
#1545000
b10010110 !
b10010110 &
b11001101110 '
b101001110110 $
b101001110110 %
1"
#1550000
0"
#1555000
b110011011 !
b110011011 &
b11111100001001 '
b111001010 $
b111001010 %
1"
#1560000
0"
#1565000
b111111000010 !
b111111000010 &
b1010000110 '
b10110110110 $
b10110110110 %
1"
#1570000
0"
#1575000
b10100001 !
b10100001 &
b1100011 '
b110010101 $
b110010101 %
1"
#1580000
0"
#1585000
b11000 !
b11000 &
b1110001011 '
b101001000110 $
b101001000110 %
1"
#1590000
0"
#1595000
b11100010 !
b11100010 &
b1101011011 '
b1100000100 $
b1100000100 %
1"
#1600000
0"
#1605000
b11010110 !
b11010110 &
b10010010101 '
b111110111 $
b111110111 %
1"
#1610000
0"
#1615000
b100100101 !
b100100101 &
b11010110 '
b11101101001 $
b11101101001 %
1"
#1620000
0"
#1625000
b110101 !
b110101 &
b11010101010 '
b101010110100 $
b101010110100 %
1"
#1630000
0"
#1635000
b110101010 !
b110101010 &
b11100011000 '
b10110001000 $
b10110001000 %
1"
#1640000
0"
#1645000
b111000110 !
b111000110 &
b100110011100 '
b100101000 $
b100101000 %
1"
#1650000
0"
#1655000
b1001100111 !
b1001100111 &
b100011001101 '
b110000101101 $
b110000101101 %
1"
#1660000
0"
#1665000
b1000110011 !
b1000110011 &
b11110110010001 '
b100011000111 $
b100011000111 %
1"
#1670000
0"
#1675000
b111101100100 !
b111101100100 &
b11101110100100 '
b110000101110 $
b110000101110 %
1"
#1680000
0"
#1685000
b111011101001 !
b111011101001 &
b11001001001010 '
b110000001000 $
b110000001000 %
1"
#1690000
0"
#1695000
b110010010010 !
b110010010010 &
b10110100101010 '
b10100011100 $
b10100011100 %
1"
#1700000
0"
#1705000
b101101001010 !
b101101001010 &
b11011000011001 '
b111011111101 $
b111011111101 %
1"
#1710000
0"
#1715000
b110110000110 !
b110110000110 &
b11110001001111 '
b11100101001 $
b11100101001 %
1"
#1720000
0"
#1725000
b111100010011 !
b111100010011 &
b11101001010 '
b100000011100 $
b100000011100 %
1"
#1730000
0"
#1735000
b111010010 !
b111010010 &
b1101011110 '
b11110000110 $
b11110000110 %
1"
#1740000
0"
#1745000
b11010111 !
b11010111 &
b10111001000 '
b100011011010 $
b100011011010 %
1"
#1750000
0"
#1755000
b101110010 !
b101110010 &
b11111110100101 '
b111000111101 $
b111000111101 %
1"
#1760000
0"
#1765000
b111111101001 !
b111111101001 &
b11011010111001 '
b11101100110 $
b11101100110 %
1"
#1770000
0"
#1775000
b110110101110 !
b110110101110 &
b11000000011 '
b110001110000 $
b110001110000 %
1"
#1780000
0"
#1785000
b110000000 !
b110000000 &
b11101011101101 '
b110001110011 $
b110001110011 %
1"
#1790000
0"
#1795000
b111010111011 !
b111010111011 &
b11111010000110 '
b110111010 $
b110111010 %
1"
#1800000
0"
#1805000
b111110100001 !
b111110100001 &
b1000000011 '
b1101011110 $
b1101011110 %
1"
#1810000
0"
#1815000
b10000000 !
b10000000 &
b11110111111011 '
b111111010 $
b111111010 %
1"
#1820000
0"
#1825000
b111101111110 !
b111101111110 &
b1110000101 '
b10111010101 $
b10111010101 %
1"
#1830000
0"
#1835000
b11100001 !
b11100001 &
b110011100111 '
b111000011010 $
b111000011010 %
1"
#1840000
0"
#1845000
b1100111001 !
b1100111001 &
b100101000111 '
b100010111001 $
b100010111001 %
1"
#1850000
0"
#1855000
b1001010001 !
b1001010001 &
b11111010100010 '
b100110111 $
b100110111 %
1"
#1860000
0"
#1865000
b111110101000 !
b111110101000 &
b11110111011111 '
b11110010110 $
b11110010110 %
1"
#1870000
0"
#1875000
b111101110111 !
b111101110111 &
b11111110100000 '
b111000000 $
b111000000 %
1"
#1880000
0"
#1885000
b111111101000 !
b111111101000 &
b1101000110 '
b11100100110 $
b11100100110 %
1"
#1890000
0"
#1895000
b11010001 !
b11010001 &
b1000110110011 '
b101010110110 $
b101010110110 %
1"
#1900000
0"
#1905000
b10001101100 !
b10001101100 &
b101100110010 '
b1101111101 $
b1101111101 %
1"
#1910000
0"
#1915000
b1011001100 !
b1011001100 &
b11100011001 '
b11111011100 $
b11111011100 %
1"
#1920000
0"
#1925000
b111000110 !
b111000110 &
b110100110101 '
b11110000110 $
b11110000110 %
1"
#1930000
0"
#1935000
b1101001101 !
b1101001101 &
b110110010101 '
b11101111000 $
b11101111000 %
1"
#1940000
0"
#1945000
b1101100101 !
b1101100101 &
b1101001010111 '
b1101111110 $
b1101111110 %
1"
#1950000
0"
#1955000
b11010010101 !
b11010010101 &
b1101001011000 '
b100011011011 $
b100011011011 %
1"
#1960000
0"
#1965000
b11010010110 !
b11010010110 &
b101101010111 '
b111011001111 $
b111011001111 %
1"
#1970000
0"
#1975000
b1011010101 !
b1011010101 &
b1010100000 '
b1101111001 $
b1101111001 %
1"
#1980000
0"
#1985000
b10101000 !
b10101000 &
b11111010100001 '
b110011111010 $
b110011111010 %
1"
#1990000
0"
#1995000
b111110101000 !
b111110101000 &
b11100000011101 '
b111001100001 $
b111001100001 %
1"
#2000000
0"
#2005000
b111000000111 !
b111000000111 &
b11110110100011 '
b100010111 $
b100010111 %
1"
#2010000
0"
#2015000
b111101101000 !
b111101101000 &
b11111111101011 '
b100010100001 $
b100010100001 %
1"
#2020000
0"
#2025000
b111111111010 !
b111111111010 &
b11010100010011 '
b110000110 $
b110000110 %
1"
#2030000
0"
#2035000
b110101000100 !
b110101000100 &
b11100110011111 '
b111001010000 $
b111001010000 %
1"
#2040000
0"
#2045000
b111001100111 !
b111001100111 &
b11100110001110 '
b111110101 $
b111110101 %
1"
#2050000
0"
#2055000
b111001100011 !
b111001100011 &
b11101001101100 '
b100000110101 $
b100000110101 %
1"
#2060000
0"
#2065000
b111010011011 !
b111010011011 &
b11101000000000 '
b101000101001 $
b101000101001 %
1"
#2070000
0"
#2075000
b111010000000 !
b111010000000 &
b11001010100011 '
b10111000001 $
b10111000001 %
1"
#2080000
0"
#2085000
b110010101000 !
b110010101000 &
b11101000010100 '
b110011000101 $
b110011000101 %
1"
#2090000
0"
#2095000
b111010000101 !
b111010000101 &
b11010011100100 '
b110010011000 $
b110010011000 %
1"
#2100000
0"
#2105000
b110100111001 !
b110100111001 &
b11100101000111 '
b1101001011 $
b1101001011 %
1"
#2110000
0"
#2115000
b111001010001 !
b111001010001 &
b1001101001 '
b101001110011 $
b101001110011 %
1"
#2120000
0"
#2125000
b10011010 !
b10011010 &
b11011100011011 '
b111011101100 $
b111011101100 %
1"
#2130000
0"
#2135000
b110111000110 !
b110111000110 &
b11100101000010 '
b111010001010 $
b111010001010 %
1"
#2140000
0"
#2145000
b111001010000 !
b111001010000 &
b11101100110100 '
b101001110 $
b101001110 %
1"
#2150000
0"
#2155000
b111011001101 !
b111011001101 &
b11100100110111 '
b100010101000 $
b100010101000 %
1"
#2160000
0"
#2165000
b111001001101 !
b111001001101 &
b11011101101100 '
b10110101001 $
b10110101001 %
1"
#2170000
0"
#2175000
b110111011011 !
b110111011011 &
b11111000101001 '
b110010100001 $
b110010100001 %
1"
#2180000
0"
#2185000
b111110001010 !
b111110001010 &
b11110001000000 '
b100001110 $
b100001110 %
1"
#2190000
0"
#2195000
b111100010000 !
b111100010000 &
b11110000000000 '
b111011100110 $
b111011100110 %
1"
#2200000
0"
#2205000
b111100000000 !
b111100000000 &
b1000111110 '
b100010011111 $
b100010011111 %
1"
#2210000
0"
#2215000
b10001111 !
b10001111 &
b11010100110100 '
b10100101010 $
b10100101010 %
1"
#2220000
0"
#2225000
b110101001101 !
b110101001101 &
b11110110111101 '
1"
#2230000
0"
#2235000
b111101101111 !
b111101101111 &
b111011001 '
b110010001101 $
b110010001101 %
1"
#2240000
0"
#2245000
b1110110 !
b1110110 &
b11111110000000 '
b11110011110 $
b11110011110 %
1"
#2250000
0"
#2255000
b111111100000 !
b111111100000 &
b111001111111 '
b111000111000 $
b111000111000 %
1"
#2260000
0"
#2265000
b1110011111 !
b1110011111 &
b11110001101 '
b100001111001 $
b100001111001 %
1"
#2270000
0"
#2275000
b111100011 !
b111100011 &
b11101011011100 '
b1111001000 $
b1111001000 %
1"
#2280000
0"
#2285000
b111010110111 !
b111010110111 &
b1000010111 '
b10111001010 $
b10111001010 %
1"
#2290000
0"
#2295000
b10000101 !
b10000101 &
b1000011 '
b100010011 $
b100010011 %
1"
#2300000
0"
#2305000
b10000 !
b10000 &
b1100011110 '
b101101011 $
b101101011 %
1"
#2310000
0"
#2315000
b11000111 !
b11000111 &
b110000010000 '
b111011000111 $
b111011000111 %
1"
#2320000
0"
#2325000
b1100000100 !
b1100000100 &
b11100001111 '
b10110110110 $
b10110110110 %
1"
#2330000
0"
#2335000
b111000011 !
b111000011 &
b11011111011 '
b10110111010 $
b10110111010 %
1"
#2340000
0"
#2345000
b110111110 !
b110111110 &
b101110100010 '
b1111000100 $
b1111000100 %
1"
#2350000
0"
#2355000
b1011101000 !
b1011101000 &
b110111111011 '
b10110111001 $
b10110111001 %
1"
#2360000
0"
#2365000
b1101111110 !
b1101111110 &
b1010011101101 '
b1110010010 $
b1110010010 %
1"
#2370000
0"
#2375000
b10100111011 !
b10100111011 &
b1001011001001 '
b101010110100 $
b101010110100 %
1"
#2380000
0"
#2385000
b10010110010 !
b10010110010 &
b11111000011 '
b1101111111 $
b1101111111 %
1"
#2390000
0"
#2395000
b111110000 !
b111110000 &
b11101111110 '
b100010000110 $
b100010000110 %
1"
#2400000
0"
#2405000
b111011111 !
b111011111 &
b11101001001011 '
b10111111010 $
b10111111010 %
1"
#2410000
0"
#2415000
b111010010010 !
b111010010010 &
b11110010110011 '
b110011110010 $
b110011110010 %
1"
#2420000
0"
#2425000
b111100101100 !
b111100101100 &
b11111011110001 '
b100110010 $
b100110010 %
1"
#2430000
0"
#2435000
b111110111100 !
b111110111100 &
b11110010100100 '
b111010111101 $
b111010111101 %
1"
#2440000
0"
#2445000
b111100101001 !
b111100101001 &
b1011011011 '
b10110000100 $
b10110000100 %
1"
#2450000
0"
#2455000
b10110110 !
b10110110 &
b1001100101 '
b110011100100 $
b110011100100 %
1"
#2460000
0"
#2465000
b10011001 !
b10011001 &
b1001010111 '
b11111001010 $
b11111001010 %
1"
#2470000
0"
#2475000
b10010101 !
b10010101 &
b100011101111 '
b110101001 $
b110101001 %
1"
#2480000
0"
